{
    "title": "Take our quiz",
    "outcomes": {
            "outcome1": {"img": "imgs/results/tricycle.jpeg", "text": "You are a... <strong>Tricycle</strong><br>Try to break out of your shell and go an adventure!"},
            "outcome2": {"img": "imgs/results/Kawasaki.jpeg", "text": "You are a... <strong>Kawasaki</strong><br>You are extremely competitive, resourceful, and focused when you set your mind to something. You are a warrior who grinds until they succeed."},
            "outcome3": {"img": "imgs/results/Ducati.jpg", "text": "You are a... <strong>Ducati</strong><br>You drip style and radiate class. You enjoy the lavishes of life: the loud, the fast, the expensive. You live your life to the fullest!"},
            "outcome4": {"img": "imgs/results/Yamaha.png", "text": "You are a... <strong>Yamaha</strong><br>You are someone who always has a solution for everything life throws your way. Down to earth and okay with getting a little dirty, you thrive in any environment!"},
            "outcome5": {"img": "imgs/results/Triumph.jpg", "text": "You are a... <strong>Triumph</strong><br>You are the empitomy of Cool. You understand the subtlety of style and your authenticity is why other's look towards you to lead."},
            "outcome6": {"img": "imgs/results/Harley-Davidson.webp", "text": "You are a... <strong>Harley-Davidson</strong><br>You are All-American, iconic, and thrive in packs of like-minded bikers with a need for adventure. You're the Boss, never to turn away from controntation."}
    },
    "questions": [
        {
            "question_name": "Choose A <span>Sport</span>",
            "question_img_url": "imgs/question_background.jpg",
            "radio_name": "favorite_sport",
            "answers": [
                {
                    "text": "Futbol",
                    "img_url": "imgs/sports/soccer.jpeg",
                    "outcome": "8"
                },
                {
                    "text": "Who knew unicycle basketball was a thing...",
                    "img_url": "imgs/sports/unicycle.JPG",
                    "outcome": "0"
                },
                {
                    "text": "Where you use your hands but call it football",
                    "img_url": "imgs/sports/football.jpeg",
                    "outcome": "10"
                },
                {
                    "text": "bounce, bounce, SLAM DUNK",
                    "img_url": "imgs/sports/basketball.jpeg",
                    "outcome": "7"
                },
                {
                    "text": "The sport where everyone falls asleep",
                    "img_url": "imgs/sports/baseball.png",
                    "outcome": "5"
                },
                {
                    "text": "Michael Phelps please come back",
                    "img_url": "imgs/sports/swimming.png",
                    "outcome": "6"
                }
            ]
        }, 
        {
            "question_name": "Choose A <span>Movie</span> Theme",
            "question_img_url": "imgs/question_background.jpg",
            "radio_name": "favorite_movie",
            "answers": [
                {
                    "text": "The cactus of movie genre",
                    "img_url": "imgs/movies/horror.png",
                    "outcome": "0"
                },
                {
                    "text": "More <3 triangles in romcoms than HS Geo.",
                    "img_url": "imgs/movies/romance.jpeg",
                    "outcome": "3"
                },
                {
                    "text": "Good classic feels",
                    "img_url": "imgs/movies/disney.jpeg",
                    "outcome": "5"
                },
                {
                    "text": "Pew pew *dramatic close-up* pew pew",
                    "img_url": "imgs/movies/action.png",
                    "outcome": "7"
                },
                {
                    "text": "More cliff hangers than actual cliffs in the world",
                    "img_url": "imgs/movies/marvel.png",
                    "outcome": "6"
                },
                {
                    "text": "Waiting for your Lou's order like...",
                    "img_url": "imgs/movies/charlie.jpeg",
                    "outcome": "10"
                }
            ]
        }, 
        {
            "question_name": "Which <span>Doggo</span> Are You?",
            "question_img_url": "imgs/question_background.jpg",
            "radio_name": "favorite_vaca",
            "answers": [
                {
                    "text": "Wilderness woofer",
                    "img_url": "imgs/vacation/forest.png",
                    "outcome": "5"
                },
                {
                    "text": "Beach boi",
                    "img_url": "imgs/vacation/beach.jpg",
                    "outcome": "4"
                },
                {
                    "text": "Dessert doggo",
                    "img_url": "imgs/vacation/desert.png",
                    "outcome": "7"
                },
                {
                    "text": "Snow pup",
                    "img_url": "imgs/vacation/snow.jpeg",
                    "outcome": "8"
                },
                {
                    "text": "City pupper",
                    "img_url": "imgs/vacation/city.png",
                    "outcome": "1"
                },
                {
                    "text": "One heckin BA doggo",
                    "img_url": "imgs/vacation/motorcycle.JPG",
                    "outcome": "10"
                }
            ]
        }, 
        {
            "question_name": "What Is Your Favorite <span>Snack</span>?",
            "question_img_url": "imgs/light.jpg",
            "radio_name": "favorite_snack",
            "answers": [
                {
                    "text": "Heard they will be out of surgery soon",
                    "img_url": "imgs/food/grapes.jpeg",
                    "outcome": "5"
                },
                {
                    "text": "Ew",
                    "img_url": "imgs/food/pickles.png",
                    "outcome": "0"
                },
                {
                    "text": "Cardboard squares sprinkled with salt",
                    "img_url": "imgs/food/wheatthins.jpeg",
                    "outcome": "2"
                },
                {
                    "text": "Pure sugar",
                    "img_url": "imgs/food/starbursts.jpg",
                    "outcome": "4"
                },
                {
                    "text": "The flaming bois that dare-devils eat",
                    "img_url": "imgs/food/cheetos.jpeg",
                    "outcome": "10"
                },
                {
                    "text": "B bananas B A N A N A S",
                    "img_url": "imgs/food/banana.jpg",
                    "outcome": "3"
                }
            ]
        }, 
        {
            "question_name": "Where Would You Rather <span>Live</span>?",
            "question_img_url": "imgs/question_background.jpg",
            "radio_name": "favorite_home",
            "answers": [
                {
                    "text": "Fancy",
                    "img_url": "imgs/homes/original.jpg",
                    "outcome": "4"
                },
                {
                    "text": "Rush hour 24/7",
                    "img_url": "imgs/homes/Skyscrapers.jpg",
                    "outcome": "2"
                },
                {
                    "text": "Heaven",
                    "img_url": "imgs/homes/shop.jpg",
                    "outcome": "10"
                },
                {
                    "text": "Beautiful roads for a nice long ride",
                    "img_url": "imgs/homes/town.jpg",
                    "outcome": "6"
                },
                {
                    "text": "Sea motorcycle",
                    "img_url": "imgs/homes/sailboat.png",
                    "outcome": "9"
                },
                {
                    "text": "Perfect for off-roading",
                    "img_url": "imgs/homes/Farm.jpg",
                    "outcome": "8"
                }
            ]
        }
    ]
}